{
  "project_info": {
    "project_number": "644324286173",
    "project_id": "ques-1b24c",
    "storage_bucket": "ques-1b24c.appspot.com"
  },
  "client": [
    {
      "client_info": {
        "mobilesdk_app_id": "1:644324286173:android:c9b5ec7a5f1b6b51e38534",
        "android_client_info": {
          "package_name": "pl.ques"
        }
      },
      "oauth_client": [
        {
          "client_id": "644324286173-5hd7fcbog3d9ufsv28k6ht4v0reahf6n.apps.googleusercontent.com",
          "client_type": 3
        }
      ],
      "api_key": [
        {
          "current_key": "AIzaSyCiPzJ_nJhPjpEf3wS5EDhrtXyEXukE-4Y"
        }
      ],
      "services": {
        "appinvite_service": {
          "other_platform_oauth_client": [
            {
              "client_id": "644324286173-5hd7fcbog3d9ufsv28k6ht4v0reahf6n.apps.googleusercontent.com",
              "client_type": 3
            },
            {
              "client_id": "644324286173-u5gltv1vm8eou16b6hh7ue3ebqksmlds.apps.googleusercontent.com",
              "client_type": 2,
              "ios_info": {
                "bundle_id": "pl.ques"
              }
            }
          ]
        }
      }
    }
  ],
  "configuration_version": "1"
}